[
    {
        "Title": "Chargé d'études en génie civil à la division de la voirie de Diekirch (m/f) (réf. E00033815) (réf. F00033816)",
        "Link": "https://govjobs.public.lu/fr/postuler/postes-ouverts/postes-vacants/fonctionnaires/2025/A1/Fevrier/20250205-chargdtudesengniecivilladivisi-345049.html",
        "Education Level": "Master",
        "Job Category": "Technique et infrastructure",
        "Status": "Fonctionnaire, Employé de l'État",
        "Task": "Tâche complète",
        "Ministry": "Ministère de la Mobilité et des Travaux publics",
        "Administration/Organization": "Administration des Ponts et Chaussées",
        "Application Deadline": "19/02/2025",
        "Nationality": "Être ressortissant UE",
        "Number of Vacancies": "1",
        "Contract Type": "Admission au stage (fonctionnaire) ou CDI (employé de l’État)",
        "Group Classification": "A1",
        "adding_date": "2025-02-06T01:41:51.760904"
    },
    {
        "Title": "Chargé d'études en génie civil à la division de la voirie de Diekirch (m/f) (réf. M00033817) - Recrutement interne",
        "Link": "https://govjobs.public.lu/fr/postuler/mobilite-interne/changement-administration/2025/A1/Fevrier/20250205-chargdtudesengniecivilladivisi-345050.html",
        "Education Level": "Master",
        "Job Category": "Technique et infrastructure",
        "Status": "Fonctionnaire",
        "Task": "Tâche complète",
        "Ministry": "Ministère de la Mobilité et des Travaux publics",
        "Administration/Organization": "Administration des Ponts et Chaussées",
        "Application Deadline": "19/02/2025",
        "Nationality": "Être ressortissant UE",
        "Number of Vacancies": "1",
        "Group Classification": "A1",
        "adding_date": "2025-02-06T01:41:51.760916"
    },
    {
        "Title": "Aide socio-familial (m/f)",
        "Link": "https://govjobs.public.lu/fr/secteur-communal/postes-ouverts/salaries/2025/Fevrier/20250205-aidesociofamilialmf-345355.html",
        "Status": " Salarié à tâche intellectuelle",
        "Task": "Tâche complète",
        "Application Deadline": "23/02/2025",
        "Salary Group": "",
        "Nationality": "Être ressortissant UE",
        "Number of Vacancies": "1",
        "Contract Type": "CDI",
        "Location": "Sud",
        "adding_date": "2025-02-06T01:41:51.760966"
    },
    {
        "Title": "Conseiller-expert en urbanisme et environnement (m/f) (réf. M00033814) - Recrutement interne",
        "Link": "https://govjobs.public.lu/fr/postuler/mobilite-interne/changement-administration/2025/A1/Fevrier/20250205-conseillerexpertenurbanismeete-344910.html",
        "Education Level": "Master",
        "Job Category": "Environnement et Aménagement du territoire",
        "Status": "Fonctionnaire",
        "Task": "Tâche complète",
        "Ministry": "Ministère du Logement et de l'Aménagement du territoire",
        "Administration/Organization": "Département de l’Aménagement du territoire",
        "Application Deadline": "24/02/2025",
        "Nationality": "Avoir la nationalité luxembourgeoise",
        "Number of Vacancies": "1",
        "Group Classification": "A1",
        "adding_date": "2025-02-06T01:41:51.760976"
    },
    {
        "Title": "Chargé d’études en matière d’écosystèmes aquatiques (m/f) (réf. E00033811)",
        "Link": "https://govjobs.public.lu/fr/postuler/postes-ouverts/postes-vacants/employes/2025/A1/Fevrier/20250204-chargdtudesenmatiredcosystmesa-344958.html",
        "Education Level": "Master",
        "Job Category": "Environnement et Aménagement du territoire",
        "Status": "Employé de l'État",
        "Task": "Tâche complète",
        "Ministry": "Ministère de l'Environnement, du Climat et de la Biodiversité",
        "Administration/Organization": "Administration de la gestion de l'eau",
        "Application Deadline": "19/02/2025",
        "Nationality": "Être ressortissant UE",
        "Number of Vacancies": "1",
        "Contract Type": "CDD jusqu'au 18 décembre 2025",
        "Group Classification": "A1",
        "adding_date": "2025-02-06T01:41:51.761008"
    },
    {
        "Title": "Responsable processus de transformation et projets stratégiques (m/f) (réf. E00033827)",
        "Link": "https://govjobs.public.lu/fr/postuler/postes-ouverts/postes-vacants/employes/2025/A1/Fevrier/20250205-responsableprocessusdetransfor-345157.html",
        "Education Level": "Master",
        "Job Category": "Affaires générales",
        "Status": "Employé de l'État",
        "Task": "Tâche complète",
        "Ministry": "Ministère du Logement et de l'Aménagement du territoire",
        "Administration/Organization": "Département du Logement",
        "Application Deadline": "12/02/2025",
        "Nationality": "Avoir la nationalité luxembourgeoise",
        "Number of Vacancies": "1",
        "Contract Type": "CDI",
        "Group Classification": "A1",
        "adding_date": "2025-02-06T01:41:51.761098"
    },
    {
        "Title": "Gestionnaire administratif (m/f) (réf. E00033840)",
        "Link": "https://govjobs.public.lu/fr/postuler/postes-ouverts/postes-vacants/employes/2025/A1/Fevrier/20250205-gestionnaireadministratifmfrfe-345314.html",
        "Education Level": "Master",
        "Job Category": "Environnement et Aménagement du territoire",
        "Status": "Employé de l'État",
        "Task": "Tâche à temps partiel (50%)",
        "Ministry": "Ministère du Logement et de l'Aménagement du territoire",
        "Administration/Organization": "Département de l’Aménagement du territoire",
        "Application Deadline": "21/02/2025",
        "Nationality": "Avoir la nationalité luxembourgeoise",
        "Number of Vacancies": "1",
        "Contract Type": "CDD jusqu'au 31 décembre 2025",
        "Group Classification": "A1",
        "adding_date": "2025-02-06T01:41:51.761131"
    },
    {
        "Title": "Spécialiste « Business Intelligence » (m/f) (réf. M00033824) - Recrutement interne",
        "Link": "https://govjobs.public.lu/fr/postuler/mobilite-interne/changement-administration/2025/A1/Fevrier/20250205-spcialistebusinessintelligence-345125.html",
        "Education Level": "Master",
        "Job Category": "Cohésion sociale",
        "Status": "Fonctionnaire",
        "Task": "Tâche complète",
        "Ministry": "Ministère de la Famille, des Solidarités, du Vivre ensemble et de l'Accueil",
        "Administration/Organization": "Département ministériel",
        "Application Deadline": "26/02/2025",
        "Nationality": "Avoir la nationalité luxembourgeoise",
        "Number of Vacancies": "1",
        "Group Classification": "A1",
        "adding_date": "2025-02-06T01:41:51.761400"
    },
    {
        "Title": "Conseiller-expert en urbanisme et environnement (m/f) (réf. E00033812) (réf. F00033813)",
        "Link": "https://govjobs.public.lu/fr/postuler/postes-ouverts/postes-vacants/fonctionnaires/2025/A1/Fevrier/20250205-conseillerexpertenurbanismeete-344908.html",
        "Education Level": "Master",
        "Job Category": "Environnement et Aménagement du territoire",
        "Status": "Fonctionnaire, Employé de l'État",
        "Task": "Tâche complète",
        "Ministry": "Ministère du Logement et de l'Aménagement du territoire",
        "Administration/Organization": "Département de l’Aménagement du territoire",
        "Application Deadline": "24/02/2025",
        "Nationality": "Avoir la nationalité luxembourgeoise",
        "Number of Vacancies": "1",
        "Contract Type": "Admission au stage (fonctionnaire) ou CDI (employé de l’État)",
        "Group Classification": "A1",
        "adding_date": "2025-02-06T01:41:51.761413"
    },
    {
        "Title": "Gestionnaire administratif (m/f) (réf. E00033841)",
        "Link": "https://govjobs.public.lu/fr/postuler/postes-ouverts/postes-vacants/employes/2025/A2/Fevrier/20250205-gestionnaireadministratifmfrfe-345316.html",
        "Education Level": "Bachelor",
        "Job Category": "Environnement et Aménagement du territoire",
        "Status": "Employé de l'État",
        "Task": "Tâche à temps partiel (50%)",
        "Ministry": "Ministère du Logement et de l'Aménagement du territoire",
        "Administration/Organization": "Département de l’Aménagement du territoire",
        "Application Deadline": "21/02/2025",
        "Nationality": "Avoir la nationalité luxembourgeoise",
        "Number of Vacancies": "1",
        "Contract Type": "CDD jusqu'au 31 décembre 2025",
        "Group Classification": "A2",
        "adding_date": "2025-02-06T01:41:51.761507"
    },
    {
        "Title": "Agent en charge de l’organisation et du suivi technique des réunions des commissions parlementaires (m/f) (réf. M00033838) - Recrutement interne",
        "Link": "https://govjobs.public.lu/fr/postuler/mobilite-interne/changement-administration/2025/B1/Fevrier/20250205-agentenchargedelorganisationet-345229.html",
        "Education Level": "Diplôme de fin d’études secondaires ou diplôme de technicien",
        "Job Category": "Technologie de l'information et de la communication",
        "Status": "Fonctionnaire",
        "Task": "Tâche complète",
        "Administration/Organization": "Chambre des Députés (Administration parlementaire)",
        "Application Deadline": "21/02/2025",
        "Nationality": "Être ressortissant UE",
        "Number of Vacancies": "1",
        "Group Classification": "B1",
        "adding_date": "2025-02-06T01:41:51.761713"
    },
    {
        "Title": "Expert en sciences humaines - pédagogue (m/f) (réf. F00033820)",
        "Link": "https://govjobs.public.lu/fr/postuler/postes-ouverts/postes-vacants/fonctionnaires/2025/A1/Fevrier/20250205-expertenscienceshumainespdagog-345098.html",
        "Education Level": "Master",
        "Job Category": "Education et Formation tout au long de la vie",
        "Status": "Fonctionnaire",
        "Task": "Tâche à temps partiel (50%)",
        "Ministry": "Ministère de l'Éducation nationale, de l'Enfance et de la Jeunesse",
        "Administration/Organization": "Centre pour le développement intellectuel",
        "Application Deadline": "19/02/2025",
        "Nationality": "Être ressortissant UE",
        "Number of Vacancies": "1",
        "Contract Type": "CDI",
        "Group Classification": "A1",
        "adding_date": "2025-02-06T01:41:51.761721"
    },
    {
        "Title": "Infirmier (m/f)",
        "Link": "https://govjobs.public.lu/fr/secteur-communal/postes-ouverts/salaries/2025/Fevrier/20250205-infirmiermf-345354.html",
        "Status": " Salarié à tâche intellectuelle",
        "Task": "Tâche complète",
        "Application Deadline": "23/02/2025",
        "Salary Group": "",
        "Nationality": "Être ressortissant UE",
        "Number of Vacancies": "1",
        "Contract Type": "CDI",
        "Location": "Sud",
        "adding_date": "2025-02-06T01:41:51.761894"
    },
    {
        "Title": "Délégué à la sécurité (m/f)",
        "Link": "https://govjobs.public.lu/fr/secteur-communal/postes-ouverts/salaries/2025/Fevrier/20250205-dlgulascuritmf-345360.html",
        "Education Level": "Diplôme de fin d’études secondaires ou diplôme de technicien",
        "Status": " Salarié à tâche intellectuelle",
        "Task": "Tâche complète",
        "Application Deadline": "14/02/2025",
        "Nationality": "Être ressortissant UE",
        "Number of Vacancies": "1",
        "Contract Type": "CDI",
        "Group Classification": "B1",
        "Location": "Nord",
        "adding_date": "2025-02-06T01:41:51.761903"
    },
    {
        "Title": "Expert en sciences humaines - pédagogue (m/f) (réf. M00033821) - Recrutement interne",
        "Link": "https://govjobs.public.lu/fr/postuler/mobilite-interne/changement-administration/2025/A1/Fevrier/20250205-expertenscienceshumainespdagog-345099.html",
        "Education Level": "Master",
        "Job Category": "Education et Formation tout au long de la vie",
        "Status": "Fonctionnaire",
        "Task": "Tâche à temps partiel (50%)",
        "Ministry": "Ministère de l'Éducation nationale, de l'Enfance et de la Jeunesse",
        "Administration/Organization": "Centre pour le développement intellectuel",
        "Application Deadline": "19/02/2025",
        "Nationality": "Être ressortissant UE",
        "Number of Vacancies": "1",
        "Group Classification": "A1",
        "adding_date": "2025-02-06T01:41:51.761965"
    },
    {
        "Title": "Expert en sciences humaines - pédagogue (m/f)",
        "Link": "https://govjobs.public.lu/fr/postuler/postes-ouverts/postes-vacants/decentralise/2025/A1/Fevrier/20250205-pdagoguemf-345101.html",
        "Education Level": "Master",
        "Job Category": "Education et Formation tout au long de la vie",
        "Status": "Employé de l'État",
        "Task": "Tâche à temps partiel (50%)",
        "Ministry": "Ministère de l'Éducation nationale, de l'Enfance et de la Jeunesse",
        "Administration/Organization": "Centre pour le développement intellectuel",
        "Application Deadline": "19/02/2025",
        "Nationality": "Être ressortissant UE",
        "Number of Vacancies": "1",
        "Contract Type": "CDI",
        "Group Classification": "A1",
        "adding_date": "2025-02-06T01:41:51.762008"
    },
    {
        "Title": "Agent en charge de l’organisation et du suivi technique des réunions des commissions parlementaires (m/f) (réf. M00033839) - Recrutement interne",
        "Link": "https://govjobs.public.lu/fr/postuler/mobilite-interne/changement-administration/2025/A2/Fevrier/20250205-agentenchargedelorganisationet-345235.html",
        "Education Level": "Bachelor",
        "Job Category": "Technologie de l'information et de la communication",
        "Status": "Fonctionnaire",
        "Task": "Tâche complète",
        "Administration/Organization": "Chambre des Députés (Administration parlementaire)",
        "Application Deadline": "21/02/2025",
        "Nationality": "Être ressortissant UE",
        "Number of Vacancies": "1",
        "Group Classification": "A2",
        "adding_date": "2025-02-06T01:41:51.762026"
    },
    {
        "Title": "Agent mensuration officielle (m/f) (réf. F00033842)",
        "Link": "https://govjobs.public.lu/fr/postuler/postes-ouverts/postes-vacants/fonctionnaires/2025/C1/Fevrier/20250205-agentmensurationofficiellemfrf-345351.html",
        "Education Level": "5 années ES ou DAP",
        "Job Category": "Technique et infrastructure",
        "Status": "Fonctionnaire",
        "Task": "Tâche complète",
        "Ministry": "Ministère des Finances",
        "Administration/Organization": "Administration du cadastre et de la topographie",
        "Application Deadline": "12/02/2025",
        "Nationality": "Avoir la nationalité luxembourgeoise",
        "Number of Vacancies": "1",
        "Contract Type": "CDI",
        "Group Classification": "C1",
        "adding_date": "2025-02-06T01:41:51.762059"
    },
    {
        "Title": "Data Scientist (m/f) (réf. E00033836) (réf. F00033837)",
        "Link": "https://govjobs.public.lu/fr/postuler/postes-ouverts/postes-vacants/fonctionnaires/2025/A1/Fevrier/20250205-datascientistmfrfe00033836rff0-345225.html",
        "Education Level": "Master",
        "Job Category": "Fiscalité",
        "Status": "Fonctionnaire, Employé de l'État",
        "Task": "Tâche complète",
        "Ministry": "Ministère des Finances",
        "Administration/Organization": "Administration de l'enregistrement, des domaines et de la TVA",
        "Application Deadline": "03/03/2025",
        "Nationality": "Avoir la nationalité luxembourgeoise",
        "Number of Vacancies": "1",
        "Contract Type": "Admission au stage (fonctionnaire) ou CDI (employé de l’État)",
        "Group Classification": "A1",
        "adding_date": "2025-02-06T01:41:51.762063"
    },
    {
        "Title": "Chef Service bâtiments (m/f)",
        "Link": "https://govjobs.public.lu/fr/secteur-communal/postes-ouverts/salaries/2025/Fevrier/20250205-chefservicebtimentsmf-345359.html",
        "Education Level": "Diplôme de fin d’études secondaires ou diplôme de technicien",
        "Status": " Salarié à tâche intellectuelle",
        "Task": "Tâche complète",
        "Application Deadline": "14/02/2025",
        "Nationality": "Être ressortissant UE",
        "Number of Vacancies": "1",
        "Contract Type": "CDI",
        "Group Classification": "B1",
        "Location": "Nord",
        "adding_date": "2025-02-06T01:41:51.762133"
    },
    {
        "Title": "Un aide-éducateur (m/f)",
        "Link": "https://govjobs.public.lu/fr/secteur-communal/postes-ouverts/postes-vacants/employes/2025/C1/Fevrier/20250205-unaideducateurfmdmf-345094.html",
        "Education Level": "5 années ES ou DAP",
        "Status": " Employé",
        "Application Deadline": "19/02/2025",
        "Nationality": "Être ressortissant UE",
        "Number of Vacancies": "1",
        "Contract Type": "CDI",
        "Group Classification": "C1",
        "Location": "Sud",
        "adding_date": "2025-02-06T01:41:51.762163"
    },
    {
        "Title": "Ingénieur en efficacité énergétique (m/f) (réf. M00033835) - Recrutement interne",
        "Link": "https://govjobs.public.lu/fr/postuler/mobilite-interne/changement-administration/2025/A1/Fevrier/20250205-ingnieurenefficacitnergtiquemf-345236.html",
        "Education Level": "Master",
        "Job Category": "Economie",
        "Status": "Fonctionnaire",
        "Task": "Tâche complète",
        "Ministry": "Ministère de l'Économie",
        "Administration/Organization": "Département ministériel",
        "Application Deadline": "03/03/2025",
        "Nationality": "Avoir la nationalité luxembourgeoise",
        "Number of Vacancies": "1",
        "Group Classification": "A1",
        "adding_date": "2025-02-06T01:41:51.762167"
    },
    {
        "Title": "Agent de nettoyage (m/f)",
        "Link": "https://govjobs.public.lu/fr/postuler/postes-ouverts/salaries/2025/B/Fevrier/20250205-agentdenettoyagemfmf-345190.html",
        "Job Category": "Technique et infrastructure",
        "Status": "Salarié",
        "Task": "Tâche à temps partiel (75%)",
        "Ministry": "Ministère de l'Éducation nationale, de l'Enfance et de la Jeunesse",
        "Administration/Organization": "Lycée Guillaume Kroll",
        "Application Deadline": "12/02/2025",
        "Nationality": "Être ressortissant UE",
        "Number of Vacancies": "2",
        "Contract Type": "CDI",
        "Group Classification": "B",
        "adding_date": "2025-02-06T01:41:51.762180"
    },
    {
        "Title": "Chargé des ressources humaines (m/f) (réf. E00033819)",
        "Link": "https://govjobs.public.lu/fr/postuler/postes-ouverts/postes-vacants/employes/2025/A1/Fevrier/20250205-chargdesressourceshumainesmfrf-345077.html",
        "Education Level": "Master",
        "Job Category": "Personnel et Organisation",
        "Status": "Employé de l'État",
        "Task": "Tâche complète",
        "Ministry": "Ministère des Finances",
        "Administration/Organization": "Administration des contributions directes",
        "Application Deadline": "26/02/2025",
        "Nationality": "Avoir la nationalité luxembourgeoise",
        "Number of Vacancies": "1",
        "Contract Type": "CDI",
        "Group Classification": "A1",
        "adding_date": "2025-02-06T01:41:51.762198"
    },
    {
        "Title": "Service Informatique - Employé communal, sous-groupe scientifique et technique (m/f)",
        "Link": "https://govjobs.public.lu/fr/secteur-communal/postes-ouverts/postes-vacants/employes/2025/B1/Fevrier/20250205-serviceinformatiqueemploycommu-345350.html",
        "Education Level": "Diplôme de fin d’études secondaires ou diplôme de technicien",
        "Status": " Employé",
        "Task": "Tâche complète",
        "Application Deadline": "05/03/2025",
        "Nationality": "Être ressortissant UE",
        "Number of Vacancies": "2",
        "Contract Type": "CDI",
        "Group Classification": "B1",
        "Location": "Centre",
        "adding_date": "2025-02-06T01:41:51.762207"
    },
    {
        "Title": "Ingénieur en efficacité énergétique (m/f) (réf. E00033833) (réf. F00033834)",
        "Link": "https://govjobs.public.lu/fr/postuler/postes-ouverts/postes-vacants/fonctionnaires/2025/A1/Fevrier/20250205-ingnieurenefficacitnergtiquemf-345230.html",
        "Education Level": "Master",
        "Job Category": "Economie",
        "Status": "Fonctionnaire, Employé de l'État",
        "Task": "Tâche complète",
        "Ministry": "Ministère de l'Économie",
        "Administration/Organization": "Département ministériel",
        "Application Deadline": "03/03/2025",
        "Nationality": "Avoir la nationalité luxembourgeoise",
        "Number of Vacancies": "1",
        "Contract Type": "Admission au stage (fonctionnaire) ou CDI (employé de l’État)",
        "Group Classification": "A1",
        "adding_date": "2025-02-06T01:41:51.762212"
    },
    {
        "Title": "Spécialiste « Business Intelligence » (m/f) (réf. E00033822) (réf. F00033823)",
        "Link": "https://govjobs.public.lu/fr/postuler/postes-ouverts/postes-vacants/fonctionnaires/2025/A1/Fevrier/20250205-spcialistebusinessintelligence-345122.html",
        "Education Level": "Master",
        "Job Category": "Cohésion sociale",
        "Status": "Fonctionnaire, Employé de l'État",
        "Task": "Tâche complète",
        "Ministry": "Ministère de la Famille, des Solidarités, du Vivre ensemble et de l'Accueil",
        "Administration/Organization": "Département ministériel",
        "Application Deadline": "26/02/2025",
        "Nationality": "Avoir la nationalité luxembourgeoise",
        "Number of Vacancies": "1",
        "Contract Type": "Admission au stage (fonctionnaire) ou CDI (employé de l’État)",
        "Group Classification": "A1",
        "adding_date": "2025-02-06T01:41:51.762225"
    },
    {
        "Title": "Agent administratif (m/f) (réf. E00033829)",
        "Link": "https://govjobs.public.lu/fr/postuler/postes-ouverts/postes-vacants/employes/2025/C1/Fevrier/20250205-agentadministratifmfrfe0003382-345171.html",
        "Education Level": "5 années ES ou DAP",
        "Job Category": "Justice",
        "Status": "Employé de l'État",
        "Task": "Tâche complète",
        "Ministry": "Ministère de la Justice",
        "Administration/Organization": "Administration judiciaire",
        "Application Deadline": "19/02/2025",
        "Nationality": "Avoir la nationalité luxembourgeoise",
        "Number of Vacancies": "1",
        "Contract Type": "CDD jusqu'au 4 février 2026",
        "Group Classification": "C1",
        "adding_date": "2025-02-06T01:41:51.762295"
    },
    {
        "Title": "Spécialiste « Business Intelligence » (m/f) (réf. E00033825) (réf. F00033826)",
        "Link": "https://govjobs.public.lu/fr/postuler/postes-ouverts/postes-vacants/fonctionnaires/2025/A2/Fevrier/20250205-spcialistebusinessintelligence-345116.html",
        "Education Level": "Bachelor",
        "Job Category": "Cohésion sociale",
        "Status": "Fonctionnaire, Employé de l'État",
        "Task": "Tâche complète",
        "Ministry": "Ministère de la Famille, des Solidarités, du Vivre ensemble et de l'Accueil",
        "Administration/Organization": "Département ministériel",
        "Application Deadline": "26/02/2025",
        "Nationality": "Avoir la nationalité luxembourgeoise",
        "Number of Vacancies": "1",
        "Contract Type": "Admission au stage (fonctionnaire) ou CDI (employé de l’État)",
        "Group Classification": "A2",
        "adding_date": "2025-02-06T01:41:51.762356"
    },
    {
        "Title": "Data Analyst (m/f) (réf. E00033831)",
        "Link": "https://govjobs.public.lu/fr/postuler/postes-ouverts/postes-vacants/employes/2025/A1/Fevrier/20250205-dataanalystemfrfe00033831-345188.html",
        "Education Level": "Master",
        "Job Category": "Technologie de l'information et de la communication",
        "Status": "Employé de l'État",
        "Task": "Tâche complète",
        "Ministry": "Ministère de la Digitalisation",
        "Administration/Organization": "Centre des technologies de l'information de l'État",
        "Application Deadline": "05/03/2025",
        "Nationality": "Être ressortissant UE",
        "Number of Vacancies": "1",
        "Contract Type": "CDI",
        "Group Classification": "A1",
        "adding_date": "2025-02-06T01:41:51.762424"
    },
    {
        "Title": "Spécialiste « Business Intelligence » (m/f) (réf. M00033828) - Recrutement interne",
        "Link": "https://govjobs.public.lu/fr/postuler/mobilite-interne/changement-administration/2025/A2/Fevrier/20250205-spcialistebusinessintelligence-345121.html",
        "Education Level": "Bachelor",
        "Job Category": "Cohésion sociale",
        "Status": "Fonctionnaire",
        "Task": "Tâche complète",
        "Ministry": "Ministère de la Famille, des Solidarités, du Vivre ensemble et de l'Accueil",
        "Administration/Organization": "Département ministériel",
        "Application Deadline": "26/02/2025",
        "Nationality": "Avoir la nationalité luxembourgeoise",
        "Number of Vacancies": "1",
        "Group Classification": "A2",
        "adding_date": "2025-02-06T01:41:51.762470"
    },
    {
        "Title": "Expert en formation (m/f) (réf. E00033818)",
        "Link": "https://govjobs.public.lu/fr/postuler/postes-ouverts/postes-vacants/employes/2025/B1/Fevrier/20250205-expertenformationmfrfe00033818-345073.html",
        "Education Level": "Diplôme de fin d’études secondaires ou diplôme de technicien",
        "Job Category": "Affaires générales",
        "Status": "Employé de l'État",
        "Task": "Tâche complète",
        "Ministry": "Ministère des Finances",
        "Administration/Organization": "Administration des contributions directes",
        "Application Deadline": "12/02/2025",
        "Nationality": "Avoir la nationalité luxembourgeoise",
        "Number of Vacancies": "1",
        "Contract Type": "CDI",
        "Group Classification": "B1",
        "adding_date": "2025-02-06T01:41:51.762507"
    }
]